prepup
