Metadata-Version: 2.1
Name: prepup
Version: 0.1.5
Summary: Prepup is a free, open-source package that lets you open, explore, visualize, and pre-process datasets in your Computer's Terminal.
Author: Sudhanshu Mukherjee
Author-email: sudhanshumukherjeexx@gmail.com
Classifier: Programming Language :: Python :: 3
Classifier: License :: OSI Approved :: MIT License
Classifier: Operating System :: OS Independent
Requires-Python: >=3.5
License-File: LICENSE
License-File: AUTHORS.rst
